opensarlab_controlbtn/__init__.py
opensarlab_controlbtn/_version.py
opensarlab_controlbtn/labextension/build_log.json
opensarlab_controlbtn/labextension/package.json
opensarlab_controlbtn/labextension/static/lib_index_js.784024dead04abade15d.js
opensarlab_controlbtn/labextension/static/lib_index_js.784024dead04abade15d.js.map
opensarlab_controlbtn/labextension/static/remoteEntry.7932e28a9bbcea31c7ed.js
opensarlab_controlbtn/labextension/static/remoteEntry.7932e28a9bbcea31c7ed.js.map
opensarlab_controlbtn/labextension/static/style.js
opensarlab_controlbtn/labextension/static/style_index_js.9746d395bb8e3b279c96.js
opensarlab_controlbtn/labextension/static/style_index_js.9746d395bb8e3b279c96.js.map
opensarlab_controlbtn/labextension/static/vendors-node_modules_css-loader_dist_runtime_api_js-node_modules_css-loader_dist_runtime_cssW-72eba1.6dc5fb10fc8143f2bc70.js
opensarlab_controlbtn/labextension/static/vendors-node_modules_css-loader_dist_runtime_api_js-node_modules_css-loader_dist_runtime_cssW-72eba1.6dc5fb10fc8143f2bc70.js.map
opensarlab_controlbtn/labextension/static/vendors-node_modules_jupyterlab-topbar_lib_index_js.e4a75d5d605b8000123e.js
opensarlab_controlbtn/labextension/static/vendors-node_modules_jupyterlab-topbar_lib_index_js.e4a75d5d605b8000123e.js.map
opensarlab_controlbtn-1.0.1.data/data/share/jupyter/labextensions/opensarlab-controlbtn/build_log.json
opensarlab_controlbtn-1.0.1.data/data/share/jupyter/labextensions/opensarlab-controlbtn/install.json
opensarlab_controlbtn-1.0.1.data/data/share/jupyter/labextensions/opensarlab-controlbtn/package.json
opensarlab_controlbtn-1.0.1.data/data/share/jupyter/labextensions/opensarlab-controlbtn/static/lib_index_js.784024dead04abade15d.js
opensarlab_controlbtn-1.0.1.data/data/share/jupyter/labextensions/opensarlab-controlbtn/static/lib_index_js.784024dead04abade15d.js.map
opensarlab_controlbtn-1.0.1.data/data/share/jupyter/labextensions/opensarlab-controlbtn/static/remoteEntry.7932e28a9bbcea31c7ed.js
opensarlab_controlbtn-1.0.1.dist-info/LICENSE
opensarlab_controlbtn-1.0.1.dist-info/METADATA
opensarlab_controlbtn-1.0.1.dist-info/WHEEL
opensarlab_controlbtn-1.0.1.dist-info/top_level.txt
opensarlab_controlbtn-1.0.1.dist-info/RECORD
